pyw/__init__.py
pyw/secret/__init__.py
pyw_secret-0.0.0.post1.dist-info/METADATA
pyw_secret-0.0.0.post1.dist-info/WHEEL
pyw_secret-0.0.0.post1.dist-info/licenses/LICENSE
pyw_secret-0.0.0.post1.dist-info/RECORD
